leettools/README.md
leettools/__init__.py
leettools/context_manager.py
leettools/requirements.txt
leettools/settings.py
leettools/chat/__init__.py
leettools/chat/chat_utils.py
leettools/chat/history_manager.py
leettools/chat/_impl/__init__.py
leettools/chat/_impl/duckdb/__init__.py
leettools/chat/_impl/duckdb/chat_history_duckdb_schema.py
leettools/chat/_impl/duckdb/history_manager_duckdb.py
leettools/chat/_utils/__init__.py
leettools/chat/_utils/position_util.py
leettools/chat/schemas/chat_history.py
leettools/cli/__init__.py
leettools/cli/cli.py
leettools/cli/cli_utils.py
leettools/cli/options_common.py
leettools/cli/chunker/__init__.py
leettools/cli/chunker/chunker_base.py
leettools/cli/chunker/chunker_cli.py
leettools/cli/chunker/chunker_text2chunks.py
leettools/cli/doc/__init__.py
leettools/cli/doc/doc_cli.py
leettools/cli/doc/doc_list.py
leettools/cli/doc/doc_list_all_segments.py
leettools/cli/doc/doc_list_segments.py
leettools/cli/doc/doc_print.py
leettools/cli/doc/doc_remove.py
leettools/cli/doc/doc_summarize.py
leettools/cli/docsink/__init__.py
leettools/cli/docsink/docsink_cli.py
leettools/cli/docsink/docsink_list.py
leettools/cli/docsink/docsink_remove.py
leettools/cli/docsrc/__init__.py
leettools/cli/docsrc/docsrc_cli.py
leettools/cli/docsrc/docsrc_ingest.py
leettools/cli/docsrc/docsrc_list.py
leettools/cli/docsrc/docsrc_remove.py
leettools/cli/flow/__init__.py
leettools/cli/flow/flow_cli.py
leettools/cli/kb/__init__.py
leettools/cli/kb/kb_add_local.py
leettools/cli/kb/kb_add_local_dir.py
leettools/cli/kb/kb_add_search.py
leettools/cli/kb/kb_add_url.py
leettools/cli/kb/kb_add_url_list.py
leettools/cli/kb/kb_cli.py
leettools/cli/kb/kb_create.py
leettools/cli/kb/kb_info.py
leettools/cli/kb/kb_ingest.py
leettools/cli/kb/kb_list.py
leettools/cli/kb/kb_list_db.py
leettools/cli/kb/kb_remove.py
leettools/cli/llm/__init__.py
leettools/cli/llm/llm_cli.py
leettools/cli/llm/llm_inference.py
leettools/cli/parser/__init__.py
leettools/cli/parser/parser_base.py
leettools-1.0.17.dist-info/METADATA
leettools-1.0.17.dist-info/WHEEL
leettools-1.0.17.dist-info/entry_points.txt
leettools-1.0.17.dist-info/licenses/LICENSE
leettools-1.0.17.dist-info/RECORD
