Metadata-Version: 2.4
Name: leettools
Version: 1.0.17
Summary: AI Search Workflow with Document Pipelines.
Project-URL: Homepage, https://github.com/leettools-dev/leettools
Project-URL: Bug Tracker, https://github.com/leettools-dev/leettools/issues
Author-email: LeetTools-dev <leettools@gmail.com>
License-File: LICENSE
Classifier: License :: OSI Approved :: Apache Software License
Classifier: Operating System :: OS Independent
Classifier: Programming Language :: Python :: 3
Requires-Python: >=3.11
Requires-Dist: aiofiles==23.2.1
Requires-Dist: babel==2.16.0
Requires-Dist: beautifulsoup4==4.12.3
Requires-Dist: chonkie==0.5.1
Requires-Dist: click==8.1.7
Requires-Dist: docling-core==2.21.1
Requires-Dist: docling==2.25.2
Requires-Dist: duckdb==1.1.3
Requires-Dist: fastapi==0.109.2
Requires-Dist: firecrawl-py==1.12.0
Requires-Dist: httpx==0.27.2
Requires-Dist: jinja2==3.1.3
Requires-Dist: langchain-community==0.3.15
Requires-Dist: langid==1.1.6
Requires-Dist: markdownify==0.13.1
Requires-Dist: nltk==3.8.1
Requires-Dist: openai==1.59.7
Requires-Dist: psutil==5.9.8
Requires-Dist: pydantic==2.10.3
Requires-Dist: python-dotenv==1.0.1
Requires-Dist: pyyaml==6.0.2
Requires-Dist: requests==2.32.3
Requires-Dist: rich==13.9.4
Requires-Dist: scipy==1.14.1
Requires-Dist: sentence-transformers==2.5.1
Requires-Dist: tiktoken==0.8.0
Requires-Dist: tldextract==5.1.3
Requires-Dist: urllib3==2.2.3
Requires-Dist: uvicorn==0.27.1
